<?xml version="1.0" encoding="utf-8" ?>
<dwsync>
<file name="index.html" local="130397539270000000" remote="130397539270000000" testing="0" />
<file name="object_exists.html" local="130397539270000000" remote="130397539270000000" testing="0" />
<file name="object_get_depth.html" local="130397539270000000" remote="130397539270000000" testing="0" />
<file name="object_get_mask.html" local="130397539270000000" remote="130397539270000000" testing="0" />
<file name="object_get_name.html" local="130397539270000000" remote="130397539270000000" testing="0" />
<file name="object_get_parent.html" local="130397539270000000" remote="130397539270000000" testing="0" />
<file name="object_get_persistent.html" local="130397539270000000" remote="130397539270000000" testing="0" />
<file name="object_get_solid.html" local="130397539270000000" remote="130397539270000000" testing="0" />
<file name="object_get_sprite.html" local="130397539270000000" remote="130397539270000000" testing="0" />
<file name="object_get_visible.html" local="130397539270000000" remote="130397539270000000" testing="0" />
<file name="object_is_ancestor.html" local="130397539270000000" remote="130397539270000000" testing="0" />
<file name="object_set_depth.html" local="130397539270000000" remote="130397539270000000" testing="0" />
<file name="object_set_mask.html" local="130397539270000000" remote="130397539270000000" testing="0" />
<file name="object_set_parent.html" local="130397539270000000" remote="130397539270000000" testing="0" />
<file name="object_set_persistent.html" local="130397539270000000" remote="130397539270000000" testing="0" />
<file name="object_set_solid.html" local="130397539270000000" remote="130397539270000000" testing="0" />
<file name="object_set_sprite.html" local="130397539270000000" remote="130397539270000000" testing="0" />
<file name="object_set_visible.html" local="130397539270000000" remote="130397539270000000" testing="0" />
</dwsync>