<?xml version="1.0" encoding="utf-8" ?>
<dwsync>
<file name="filename_change_ext.html" local="130397539270000000" remote="130397539270000000" testing="0" />
<file name="filename_dir.html" local="130397539270000000" remote="130397539270000000" testing="0" />
<file name="filename_drive.html" local="130397539270000000" remote="130397539270000000" testing="0" />
<file name="filename_ext.html" local="130397539270000000" remote="130397539270000000" testing="0" />
<file name="filename_name.html" local="130397539270000000" remote="130397539270000000" testing="0" />
<file name="filename_path.html" local="130397539270000000" remote="130397539270000000" testing="0" />
<file name="file_attributes.html" local="130397539270000000" remote="130397539270000000" testing="0" />
<file name="file_copy.html" local="130397539270000000" remote="130397539270000000" testing="0" />
<file name="file_delete.html" local="130397539270000000" remote="130397539270000000" testing="0" />
<file name="file_exists.html" local="130397539270000000" remote="130397539270000000" testing="0" />
<file name="file_find_close.html" local="130397539270000000" remote="130397539270000000" testing="0" />
<file name="file_find_first.html" local="130397539270000000" remote="130397539270000000" testing="0" />
<file name="file_find_next.html" local="130397539270000000" remote="130397539270000000" testing="0" />
<file name="file_rename.html" local="130397539270000000" remote="130397539270000000" testing="0" />
<file name="get_open_filename.html" local="130397539270000000" remote="130397539270000000" testing="0" />
<file name="get_open_filename_ext.html" local="130397539270000000" remote="130397539270000000" testing="0" />
<file name="get_save_filename.html" local="130397539270000000" remote="130397539270000000" testing="0" />
<file name="get_save_filename_ext.html" local="130397539270000000" remote="130397539270000000" testing="0" />
<file name="index.html" local="130397539270000000" remote="130397539270000000" testing="0" />
</dwsync>