<?xml version="1.0" encoding="utf-8" ?>
<dwsync>
<file name="index.html" local="130397539270000000" remote="130397539270000000" testing="0" />
<file name="shaders_are_supported.html" local="130397539270000000" remote="130397539270000000" testing="0" />
<file name="shader_enable_corner_id.html" local="130397539270000000" remote="130397539270000000" testing="0" />
<file name="shader_get_sampler_index.html" local="130397539270000000" remote="130397539270000000" testing="0" />
<file name="shader_get_uniform.html" local="130397539270000000" remote="130397539270000000" testing="0" />
<file name="shader_is_compiled.html" local="130397539270000000" remote="130397539270000000" testing="0" />
<file name="shader_reset.html" local="130397539270000000" remote="130397539270000000" testing="0" />
<file name="shader_set.html" local="130397539270000000" remote="130397539270000000" testing="0" />
<file name="shader_set_uniform_f.html" local="130397539270000000" remote="130397539270000000" testing="0" />
<file name="shader_set_uniform_f_array.html" local="130397539270000000" remote="130397539270000000" testing="0" />
<file name="shader_set_uniform_i.html" local="130397539270000000" remote="130397539270000000" testing="0" />
<file name="shader_set_uniform_i_array.html" local="130397539270000000" remote="130397539270000000" testing="0" />
<file name="shader_set_uniform_matrix.html" local="130397539270000000" remote="130397539270000000" testing="0" />
<file name="shader_set_uniform_matrix_array.html" local="130397539270000000" remote="130397539270000000" testing="0" />
</dwsync>