<?xml version="1.0" encoding="utf-8" ?>
<dwsync>
<file name="Action_Blocks.png" local="130389765380000000" remote="130389765380000000" testing="0" />
<file name="Action_Expression.png" local="130389765380000000" remote="130389765380000000" testing="0" />
<file name="Add_Action.png" local="130389765380000000" remote="130389765380000000" testing="0" />
<file name="align_grid.png" local="130389765380000000" remote="130389765380000000" testing="0" />
<file name="Autocomplete.png" local="130389765380000000" remote="130389765380000000" testing="0" />
<file name="AutoComplete_Image.png" local="130389765380000000" remote="130389765380000000" testing="0" />
<file name="begin.png" local="130389765380000000" remote="130389765380000000" testing="0" />
<file name="bounce.png" local="130389765380000000" remote="130389765380000000" testing="0" />
<file name="change.png" local="130389765380000000" remote="130389765380000000" testing="0" />
<file name="color_picker.png" local="130391393170000000" remote="130391393170000000" testing="0" />
<file name="comment.png" local="130389765380000000" remote="130389765380000000" testing="0" />
<file name="Config_Manager.png" local="130389765380000000" remote="130389765380000000" testing="0" />
<file name="createEXE.png" local="130389765380000000" remote="130389765380000000" testing="0" />
<file name="createinstance.png" local="130389765380000000" remote="130389765380000000" testing="0" />
<file name="create_motion.png" local="130389765380000000" remote="130389765380000000" testing="0" />
<file name="create_multiple.png" local="130389765380000000" remote="130389765380000000" testing="0" />
<file name="current_room.png" local="130389765380000000" remote="130389765380000000" testing="0" />
<file name="DebugBar.png" local="130389765380000000" remote="130389765380000000" testing="0" />
<file name="Debug_Add.png" local="130389765380000000" remote="130389765380000000" testing="0" />
<file name="Debug_Change.png" local="130389765380000000" remote="130389765380000000" testing="0" />
<file name="Debug_Clear.png" local="130389765380000000" remote="130389765380000000" testing="0" />
<file name="Debug_ClearCache.png" local="130391414650000000" remote="130391414650000000" testing="0" />
<file name="Debug_Pause.png" local="130389765380000000" remote="130389765380000000" testing="0" />
<file name="Debug_Play.png" local="130389765380000000" remote="130389765380000000" testing="0" />
<file name="Debug_restart.png" local="130389765380000000" remote="130389765380000000" testing="0" />
<file name="Debug_Script.png" local="130389765380000000" remote="130389765380000000" testing="0" />
<file name="Debug_Step.png" local="130389765380000000" remote="130389765380000000" testing="0" />
<file name="Debug_Stop.png" local="130389765380000000" remote="130389765380000000" testing="0" />
<file name="Depth_Order.png" local="130389765380000000" remote="130389765380000000" testing="0" />
<file name="destroy.png" local="130389765380000000" remote="130389765380000000" testing="0" />
<file name="destroy_at.png" local="130389765380000000" remote="130389765380000000" testing="0" />
<file name="drawself.png" local="130389765380000000" remote="130389765380000000" testing="0" />
<file name="draw_arrow.png" local="130389765380000000" remote="130389765380000000" testing="0" />
<file name="draw_background.png" local="130389765380000000" remote="130389765380000000" testing="0" />
<file name="draw_ellipse.png" local="130389765380000000" remote="130389765380000000" testing="0" />
<file name="draw_ellipse_gradient.png" local="130389765380000000" remote="130389765380000000" testing="0" />
<file name="draw_gradient_hor.png" local="130389765380000000" remote="130389765380000000" testing="0" />
<file name="draw_gradient_vert.png" local="130389765380000000" remote="130389765380000000" testing="0" />
<file name="draw_health.png" local="130389765380000000" remote="130389765380000000" testing="0" />
<file name="draw_life.png" local="130389765380000000" remote="130389765380000000" testing="0" />
<file name="draw_life_images.png" local="130389765380000000" remote="130389765380000000" testing="0" />
<file name="draw_line.png" local="130389765380000000" remote="130389765380000000" testing="0" />
<file name="draw_rectangle.png" local="130389765380000000" remote="130389765380000000" testing="0" />
<file name="draw_score.png" local="130389765380000000" remote="130389765380000000" testing="0" />
<file name="draw_sprite.png" local="130389765380000000" remote="130389765380000000" testing="0" />
<file name="draw_text.png" local="130389765380000000" remote="130389765380000000" testing="0" />
<file name="draw_text_scaled.png" local="130389765380000000" remote="130389765380000000" testing="0" />
<file name="draw_variable.png" local="130389765380000000" remote="130389765380000000" testing="0" />
<file name="else.png" local="130389765380000000" remote="130389765380000000" testing="0" />
<file name="end.png" local="130389765380000000" remote="130389765380000000" testing="0" />
<file name="end_game.png" local="130389765380000000" remote="130389765380000000" testing="0" />
<file name="ErrorReport.png" local="130389765380000000" remote="130389765380000000" testing="0" />
<file name="Event_Collision.png" local="130389765380000000" remote="130389765380000000" testing="0" />
<file name="Event_Create.png" local="130389765380000000" remote="130389765380000000" testing="0" />
<file name="Event_Destroy.png" local="130389765380000000" remote="130389765380000000" testing="0" />
<file name="Event_Draw.png" local="130389765380000000" remote="130389765380000000" testing="0" />
<file name="Event_Keyboard.png" local="130389765380000000" remote="130389765380000000" testing="0" />
<file name="Event_Keypress.png" local="130389765380000000" remote="130389765380000000" testing="0" />
<file name="Event_Keyrelease.png" local="130389765380000000" remote="130389765380000000" testing="0" />
<file name="Event_Mouse.png" local="130389765380000000" remote="130389765380000000" testing="0" />
<file name="Event_Other.png" local="130389765380000000" remote="130389765380000000" testing="0" />
<file name="Event_Step.png" local="130389765380000000" remote="130389765380000000" testing="0" />
<file name="Event_Timer.png" local="130389765380000000" remote="130389765380000000" testing="0" />
<file name="Event_Trigger.png" local="130389765380000000" remote="130389765380000000" testing="0" />
<file name="Event_URLOpen.png" local="130389765380000000" remote="130389765380000000" testing="0" />
<file name="Event_Web.png" local="130389765380000000" remote="130389765380000000" testing="0" />
<file name="execute_code.png" local="130389765380000000" remote="130389765380000000" testing="0" />
<file name="execute_script.png" local="130389765380000000" remote="130389765380000000" testing="0" />
<file name="exit.png" local="130389765380000000" remote="130389765380000000" testing="0" />
<file name="explosion.png" local="130389765380000000" remote="130389765380000000" testing="0" />
<file name="form_background.png" local="130389765380000000" remote="130389765380000000" testing="0" />
<file name="form_background_advanced.png" local="130389765380000000" remote="130389765380000000" testing="0" />
<file name="Form_CodeboxName.png" local="130389765380000000" remote="130389765380000000" testing="0" />
<file name="Form_CodeComments.png" local="130389765380000000" remote="130389765380000000" testing="0" />
<file name="form_constants.png" local="130389765380000000" remote="130389765380000000" testing="0" />
<file name="form_control_actions.png" local="130389765380000000" remote="130389765380000000" testing="0" />
<file name="form_datafile.png" local="130389765380000000" remote="130389765380000000" testing="0" />
<file name="Form_debug.png" local="130389765380000000" remote="130389765380000000" testing="0" />
<file name="form_event_panel.png" local="130389765380000000" remote="130389765380000000" testing="0" />
<file name="form_event_selector.png" local="130389765380000000" remote="130389765380000000" testing="0" />
<file name="form_extensions.png" local="130389765380000000" remote="130389765380000000" testing="0" />
<file name="form_extensions_install.png" local="130389765380000000" remote="130389765380000000" testing="0" />
<file name="form_font.png" local="130389765380000000" remote="130389765380000000" testing="0" />
<file name="form_font_2.png" local="130389765380000000" remote="130389765380000000" testing="0" />
<file name="form_GameInfo.png" local="130389765380000000" remote="130389765380000000" testing="0" />
<file name="form_image_editor.png" local="130389765380000000" remote="130389765380000000" testing="0" />
<file name="form_Instance_Order.png" local="130391401760000000" remote="130391401760000000" testing="0" />
<file name="form_mask.png" local="130389765380000000" remote="130389765380000000" testing="0" />
<file name="Form_Object.png" local="130389765380000000" remote="130389765380000000" testing="0" />
<file name="form_path.png" local="130389765380000000" remote="130389765380000000" testing="0" />
<file name="form_preferences.png" local="130389765380000000" remote="130389765380000000" testing="0" />
<file name="form_room.png" local="130389765380000000" remote="130389765380000000" testing="0" />
<file name="form_room_backgrounds.png" local="130389765380000000" remote="130389765380000000" testing="0" />
<file name="form_room_controls.png" local="130391401760000000" remote="130391401760000000" testing="0" />
<file name="form_room_objects.png" local="130389765380000000" remote="130389765380000000" testing="0" />
<file name="form_room_settings.png" local="130389765380000000" remote="130389765380000000" testing="0" />
<file name="form_room_tiles.png" local="130389765380000000" remote="130389765380000000" testing="0" />
<file name="form_room_tilestab.png" local="130389765380000000" remote="130389765380000000" testing="0" />
<file name="form_room_views.png" local="130389765380000000" remote="130389765380000000" testing="0" />
<file name="form_script.png" local="130389765380000000" remote="130389765380000000" testing="0" />
<file name="form_script2.png" local="130389765380000000" remote="130389765380000000" testing="0" />
<file name="form_shaders.png" local="130391406060000000" remote="130391406060000000" testing="0" />
<file name="form_sound.png" local="130389765380000000" remote="130389765380000000" testing="0" />
<file name="form_sprite.png" local="130389765380000000" remote="130389765380000000" testing="0" />
<file name="form_sprite_editor.png" local="130389765380000000" remote="130389765380000000" testing="0" />
<file name="form_timeline.png" local="130389765380000000" remote="130389765380000000" testing="0" />
<file name="form_trigger.png" local="130389765380000000" remote="130389765380000000" testing="0" />
<file name="fullscreen.png" local="130389765380000000" remote="130389765380000000" testing="0" />
<file name="Getting_Started_Object_Image.png" local="130389765380000000" remote="130389765380000000" testing="0" />
<file name="Getting_Started_Overview_Image.png" local="130389765380000000" remote="130389765380000000" testing="0" />
<file name="Getting_Started_Room_Image.png" local="130389765380000000" remote="130389765380000000" testing="0" />
<file name="goto_room.png" local="130389765380000000" remote="130389765380000000" testing="0" />
<file name="GUI_Image.png" local="130389765380000000" remote="130389765380000000" testing="0" />
<file name="highscore_clear.png" local="130389765380000000" remote="130389765380000000" testing="0" />
<file name="if.png" local="130389765380000000" remote="130389765380000000" testing="0" />
<file name="if_alligned.png" local="130389765380000000" remote="130389765380000000" testing="0" />
<file name="if_collision.png" local="130389765380000000" remote="130389765380000000" testing="0" />
<file name="if_dice.png" local="130389765380000000" remote="130389765380000000" testing="0" />
<file name="if_empty.png" local="130389765380000000" remote="130389765380000000" testing="0" />
<file name="if_health.png" local="130389765380000000" remote="130389765380000000" testing="0" />
<file name="if_life.png" local="130389765380000000" remote="130389765380000000" testing="0" />
<file name="if_mouse.png" local="130389765380000000" remote="130389765380000000" testing="0" />
<file name="if_next_room.png" local="130389765380000000" remote="130389765380000000" testing="0" />
<file name="if_number.png" local="130389765380000000" remote="130389765380000000" testing="0" />
<file name="if_object.png" local="130389765380000000" remote="130389765380000000" testing="0" />
<file name="if_question.png" local="130389765380000000" remote="130389765380000000" testing="0" />
<file name="if_score.png" local="130389765380000000" remote="130389765380000000" testing="0" />
<file name="if_sound.png" local="130389765380000000" remote="130389765380000000" testing="0" />
<file name="if_variable.png" local="130389765380000000" remote="130389765380000000" testing="0" />
<file name="inherited.png" local="130389765380000000" remote="130389765380000000" testing="0" />
<file name="licensescreen.png" local="130389765380000000" remote="130389765380000000" testing="0" />
<file name="linear_step.png" local="130389765380000000" remote="130389765380000000" testing="0" />
<file name="loadupscreen.png" local="130389765380000000" remote="130389765380000000" testing="0" />
<file name="load_game.png" local="130389765380000000" remote="130389765380000000" testing="0" />
<file name="message.png" local="130389765380000000" remote="130389765380000000" testing="0" />
<file name="move.png" local="130389765380000000" remote="130389765380000000" testing="0" />
<file name="move_contact.png" local="130389765380000000" remote="130389765380000000" testing="0" />
<file name="move_point.png" local="130389765380000000" remote="130389765380000000" testing="0" />
<file name="move_random.png" local="130389765380000000" remote="130389765380000000" testing="0" />
<file name="move_start.png" local="130389765380000000" remote="130389765380000000" testing="0" />
<file name="New_Config.png" local="130389765380000000" remote="130389765380000000" testing="0" />
<file name="next_room.png" local="130389765380000000" remote="130389765380000000" testing="0" />
<file name="partemitburst.png" local="130389765380000000" remote="130389765380000000" testing="0" />
<file name="partemitcreate.png" local="130389765380000000" remote="130389765380000000" testing="0" />
<file name="partemitdestroy.png" local="130389765380000000" remote="130389765380000000" testing="0" />
<file name="partemitstream.png" local="130389765380000000" remote="130389765380000000" testing="0" />
<file name="Particle_Sprites.png" local="130389765380000000" remote="130389765380000000" testing="0" />
<file name="partsystclear.png" local="130389765380000000" remote="130389765380000000" testing="0" />
<file name="partsystcreate.png" local="130389765380000000" remote="130389765380000000" testing="0" />
<file name="partsystdestroy.png" local="130389765380000000" remote="130389765380000000" testing="0" />
<file name="parttypecolor.png" local="130389765380000000" remote="130389765380000000" testing="0" />
<file name="parttypecreate.png" local="130389765380000000" remote="130389765380000000" testing="0" />
<file name="parttypegravity.png" local="130389765380000000" remote="130389765380000000" testing="0" />
<file name="parttypelife.png" local="130389765380000000" remote="130389765380000000" testing="0" />
<file name="parttypesecondary.png" local="130389765380000000" remote="130389765380000000" testing="0" />
<file name="parttypespeed.png" local="130389765380000000" remote="130389765380000000" testing="0" />
<file name="pathend.png" local="130389765380000000" remote="130389765380000000" testing="0" />
<file name="pathposition.png" local="130389765380000000" remote="130389765380000000" testing="0" />
<file name="pathset.png" local="130389765380000000" remote="130389765380000000" testing="0" />
<file name="pathspeed.png" local="130389765380000000" remote="130389765380000000" testing="0" />
<file name="path_kinds.png" local="130389765380000000" remote="130389765380000000" testing="0" />
<file name="path_toolbar.png" local="130389765380000000" remote="130389765380000000" testing="0" />
<file name="previous_room.png" local="130389765380000000" remote="130389765380000000" testing="0" />
<file name="primitive_types.png" local="130389765380000000" remote="130389765380000000" testing="0" />
<file name="Print.png" local="130389765380000000" remote="130389765380000000" testing="0" />
<file name="repeat.png" local="130389765380000000" remote="130389765380000000" testing="0" />
<file name="replace_background.png" local="130389765380000000" remote="130389765380000000" testing="0" />
<file name="replace_sound.png" local="130389765380000000" remote="130389765380000000" testing="0" />
<file name="replace_sprite.png" local="130389765380000000" remote="130389765380000000" testing="0" />
<file name="restart_game.png" local="130389765380000000" remote="130389765380000000" testing="0" />
<file name="reverse_hdir.png" local="130389765380000000" remote="130389765380000000" testing="0" />
<file name="reverse_vdir.png" local="130389765380000000" remote="130389765380000000" testing="0" />
<file name="Room_Editor_Toolbar.png" local="130389765380000000" remote="130389765380000000" testing="0" />
<file name="save_game.png" local="130389765380000000" remote="130389765380000000" testing="0" />
<file name="Script_Toolbar.png" local="130389765380000000" remote="130389765380000000" testing="0" />
<file name="Search.png" local="130389765380000000" remote="130389765380000000" testing="0" />
<file name="setmouse.png" local="130389765380000000" remote="130389765380000000" testing="0" />
<file name="set_alarm.png" local="130389765380000000" remote="130389765380000000" testing="0" />
<file name="set_caption.png" local="130389765380000000" remote="130389765380000000" testing="0" />
<file name="set_color.png" local="130389765380000000" remote="130389765380000000" testing="0" />
<file name="set_direction.png" local="130389765380000000" remote="130389765380000000" testing="0" />
<file name="set_font.png" local="130389765380000000" remote="130389765380000000" testing="0" />
<file name="set_friction.png" local="130389765380000000" remote="130389765380000000" testing="0" />
<file name="set_gravity.png" local="130389765380000000" remote="130389765380000000" testing="0" />
<file name="set_health.png" local="130389765380000000" remote="130389765380000000" testing="0" />
<file name="set_hspeed.png" local="130389765380000000" remote="130389765380000000" testing="0" />
<file name="set_life.png" local="130389765380000000" remote="130389765380000000" testing="0" />
<file name="set_score.png" local="130389765380000000" remote="130389765380000000" testing="0" />
<file name="set_sprite.png" local="130389765380000000" remote="130389765380000000" testing="0" />
<file name="set_sprite_color.png" local="130389765380000000" remote="130389765380000000" testing="0" />
<file name="set_sprite_scale.png" local="130389765380000000" remote="130389765380000000" testing="0" />
<file name="set_variable.png" local="130389765380000000" remote="130389765380000000" testing="0" />
<file name="set_vspeed.png" local="130389765380000000" remote="130389765380000000" testing="0" />
<file name="snapshot.png" local="130389765380000000" remote="130389765380000000" testing="0" />
<file name="sound_play.png" local="130389765380000000" remote="130389765380000000" testing="0" />
<file name="sound_stop.png" local="130389765380000000" remote="130389765380000000" testing="0" />
<file name="sprite.png" local="130389765380000000" remote="130389765380000000" testing="0" />
<file name="sprites_anim_1.gif" local="130389765380000000" remote="130389765380000000" testing="0" />
<file name="sprite_dialog.png" local="130389765380000000" remote="130389765380000000" testing="0" />
<file name="stepavoid.png" local="130389765380000000" remote="130389765380000000" testing="0" />
<file name="steptowards.png" local="130389765380000000" remote="130389765380000000" testing="0" />
<file name="timeline_pause.png" local="130389765380000000" remote="130389765380000000" testing="0" />
<file name="timeline_position.png" local="130389765380000000" remote="130389765380000000" testing="0" />
<file name="timeline_set.png" local="130389765380000000" remote="130389765380000000" testing="0" />
<file name="timeline_speed.png" local="130389765380000000" remote="130389765380000000" testing="0" />
<file name="timeline_start.png" local="130389765380000000" remote="130389765380000000" testing="0" />
<file name="timeline_stop.png" local="130389765380000000" remote="130389765380000000" testing="0" />
<file name="window_position.png" local="130389765380000000" remote="130389765380000000" testing="0" />
<file name="wrap.png" local="130389765380000000" remote="130389765380000000" testing="0" />
</dwsync>